pandas_alive/__init__.py
pandas_alive/_base_chart.py
pandas_alive/base.py
pandas_alive/charts.py
pandas_alive/plotting.py
pandas_alive-2020.5.15.dist-info/LICENSE
pandas_alive-2020.5.15.dist-info/WHEEL
pandas_alive-2020.5.15.dist-info/METADATA
pandas_alive-2020.5.15.dist-info/RECORD
