Metadata-Version: 2.1
Name: pandas-alive
Version: 2020.5.15
Summary: Animated plotting extension for Pandas with Matplotlib
Home-page: https://github.com/JackMcKew/pandas_alive
License: MIT
Author: JackMcKew
Author-email: jackmckew2@gmail.com
Requires-Python: >=3.6.1,<4.0.0
Classifier: License :: OSI Approved :: MIT License
Classifier: Programming Language :: Python :: 3
Classifier: Programming Language :: Python :: 3.7
Classifier: Programming Language :: Python :: 3.8
Requires-Dist: matplotlib (>=3.2.1,<4.0.0)
Requires-Dist: pandas (>=1.0.3,<2.0.0)
Project-URL: Documentation, https://jackmckew.github.io/pandas_alive/
Project-URL: Repository, https://github.com/JackMcKew/pandas_alive
Project-URL: issues, https://github.com/JackMcKew/pandas_alive/issues
